asyncqiwi/__init__.py
asyncqiwi/currencies.py
asyncqiwi/enums.py
asyncqiwi/http.py
asyncqiwi/qiwi.py
asyncqiwi/transaction.py
asyncqiwi/utils.py
qiwi-0.0.1.dist-info/METADATA
qiwi-0.0.1.dist-info/WHEEL
qiwi-0.0.1.dist-info/top_level.txt
qiwi-0.0.1.dist-info/RECORD
